{
  "info": {
    "name": "VHS Rental API Collection",
    "_postman_id": "00000000-0000-0000-0000-000000000000",
    "schema": "https://schema.getpostman.com/json/collection/v2.1.0/collection.json"
  },
  "variable": [
    {
      "key": "baseUrl",
      "value": "http://localhost:8081"
    }
  ],
  "item": [
    {
      "name": "Users",
      "item": [
        {
          "name": "Get all users",
          "request": {
            "method": "GET",
            "header": [],
            "url": {
              "raw": "{{baseUrl}}/api/users",
              "host": [
                "{{baseUrl}}"
              ],
              "path": [
                "api",
                "users"
              ]
            }
          }
        },
        {
          "name": "Get user by id (Ana)",
          "request": {
            "method": "GET",
            "header": [],
            "url": {
              "raw": "{{baseUrl}}/api/users/1",
              "host": [
                "{{baseUrl}}"
              ],
              "path": [
                "api",
                "users",
                "1"
              ]
            }
          }
        },
        {
          "name": "Find user by email (Marko)",
          "request": {
            "method": "GET",
            "header": [],
            "url": {
              "raw": "{{baseUrl}}/api/users/find?email=marko@gmail.com",
              "host": [
                "{{baseUrl}}"
              ],
              "path": [
                "api",
                "users",
                "find"
              ],
              "query": [
                {
                  "key": "email",
                  "value": "marko@gmail.com"
                }
              ]
            }
          }
        },
        {
          "name": "Create new user",
          "request": {
            "method": "POST",
            "header": [
              {
                "key": "Content-Type",
                "value": "application/json"
              }
            ],
            "body": {
              "mode": "raw",
              "raw": "{\n  \"name\": \"Ivana\",\n  \"email\": \"ivana@example.com\"\n}"
            },
            "url": {
              "raw": "{{baseUrl}}/api/users",
              "host": [
                "{{baseUrl}}"
              ],
              "path": [
                "api",
                "users"
              ]
            }
          }
        },
        {
          "name": "Create user - duplicate email (should fail)",
          "request": {
            "method": "POST",
            "header": [
              {
                "key": "Content-Type",
                "value": "application/json"
              }
            ],
            "body": {
              "mode": "raw",
              "raw": "{\n  \"name\": \"Ana Clone\",\n  \"email\": \"ana@gmail.com\"\n}"
            },
            "url": {
              "raw": "{{baseUrl}}/api/users",
              "host": [
                "{{baseUrl}}"
              ],
              "path": [
                "api",
                "users"
              ]
            }
          }
        }
      ]
    },
    {
      "name": "VHS",
      "item": [
        {
          "name": "Get all VHS",
          "request": {
            "method": "GET",
            "header": [],
            "url": {
              "raw": "{{baseUrl}}/api/vhs",
              "host": [
                "{{baseUrl}}"
              ],
              "path": [
                "api",
                "vhs"
              ]
            }
          }
        },
        {
          "name": "Get VHS by id (Jurassic Park)",
          "request": {
            "method": "GET",
            "header": [],
            "url": {
              "raw": "{{baseUrl}}/api/vhs/1",
              "host": [
                "{{baseUrl}}"
              ],
              "path": [
                "api",
                "vhs",
                "1"
              ]
            }
          }
        },
        {
          "name": "Get VHS details (with average rating)",
          "request": {
            "method": "GET",
            "header": [],
            "url": {
              "raw": "{{baseUrl}}/api/vhs/1/details",
              "host": [
                "{{baseUrl}}"
              ],
              "path": [
                "api",
                "vhs",
                "1",
                "details"
              ]
            }
          }
        },
        {
          "name": "Create new VHS",
          "request": {
            "method": "POST",
            "header": [
              {
                "key": "Content-Type",
                "value": "application/json"
              }
            ],
            "body": {
              "mode": "raw",
              "raw": "{\n  \"title\": \"The Matrix\",\n  \"genre\": \"Sci-Fi\",\n  \"releaseYear\": 1999\n}"
            },
            "url": {
              "raw": "{{baseUrl}}/api/vhs",
              "host": [
                "{{baseUrl}}"
              ],
              "path": [
                "api",
                "vhs"
              ]
            }
          }
        },
        {
          "name": "Create VHS - invalid data (should fail validation)",
          "request": {
            "method": "POST",
            "header": [
              {
                "key": "Content-Type",
                "value": "application/json"
              }
            ],
            "body": {
              "mode": "raw",
              "raw": "{\n  \"title\": \"\",\n  \"genre\": \"Drama\",\n  \"releaseYear\": null\n}"
            },
            "url": {
              "raw": "{{baseUrl}}/api/vhs",
              "host": [
                "{{baseUrl}}"
              ],
              "path": [
                "api",
                "vhs"
              ]
            }
          }
        }
      ]
    },
    {
      "name": "Rentals",
      "item": [
        {
          "name": "Get all rentals (initially empty)",
          "request": {
            "method": "GET",
            "header": [],
            "url": {
              "raw": "{{baseUrl}}/api/rentals",
              "host": [
                "{{baseUrl}}"
              ],
              "path": [
                "api",
                "rentals"
              ]
            }
          }
        },
        {
          "name": "Create rental - Ana rents Jurassic Park (user 1, vhs 1)",
          "request": {
            "method": "POST",
            "header": [
              {
                "key": "Content-Type",
                "value": "application/json"
              }
            ],
            "body": {
              "mode": "raw",
              "raw": "{\n  \"userId\": 1,\n  \"vhsId\": 1\n}"
            },
            "url": {
              "raw": "{{baseUrl}}/api/rentals",
              "host": [
                "{{baseUrl}}"
              ],
              "path": [
                "api",
                "rentals"
              ]
            }
          }
        },
        {
          "name": "Create rental - Marko rents Terminator 2 (user 2, vhs 2)",
          "request": {
            "method": "POST",
            "header": [
              {
                "key": "Content-Type",
                "value": "application/json"
              }
            ],
            "body": {
              "mode": "raw",
              "raw": "{\n  \"userId\": 2,\n  \"vhsId\": 2\n}"
            },
            "url": {
              "raw": "{{baseUrl}}/api/rentals",
              "host": [
                "{{baseUrl}}"
              ],
              "path": [
                "api",
                "rentals"
              ]
            }
          }
        },
        {
          "name": "Create rental - same VHS already rented (should fail)",
          "request": {
            "method": "POST",
            "header": [
              {
                "key": "Content-Type",
                "value": "application/json"
              }
            ],
            "body": {
              "mode": "raw",
              "raw": "{\n  \"userId\": 3,\n  \"vhsId\": 1\n}"
            },
            "url": {
              "raw": "{{baseUrl}}/api/rentals",
              "host": [
                "{{baseUrl}}"
              ],
              "path": [
                "api",
                "rentals"
              ]
            }
          }
        },
        {
          "name": "Create rental - non-existing user (should fail)",
          "request": {
            "method": "POST",
            "header": [
              {
                "key": "Content-Type",
                "value": "application/json"
              }
            ],
            "body": {
              "mode": "raw",
              "raw": "{\n  \"userId\": 999,\n  \"vhsId\": 3\n}"
            },
            "url": {
              "raw": "{{baseUrl}}/api/rentals",
              "host": [
                "{{baseUrl}}"
              ],
              "path": [
                "api",
                "rentals"
              ]
            }
          }
        },
        {
          "name": "Create rental - invalid body (should fail validation)",
          "request": {
            "method": "POST",
            "header": [
              {
                "key": "Content-Type",
                "value": "application/json"
              }
            ],
            "body": {
              "mode": "raw",
              "raw": "{\n  \"userId\": null,\n  \"vhsId\": 0\n}"
            },
            "url": {
              "raw": "{{baseUrl}}/api/rentals",
              "host": [
                "{{baseUrl}}"
              ],
              "path": [
                "api",
                "rentals"
              ]
            }
          }
        },
        {
          "name": "Get all rentals (after creating some)",
          "request": {
            "method": "GET",
            "header": [],
            "url": {
              "raw": "{{baseUrl}}/api/rentals",
              "host": [
                "{{baseUrl}}"
              ],
              "path": [
                "api",
                "rentals"
              ]
            }
          }
        },
        {
          "name": "Get active rentals",
          "request": {
            "method": "GET",
            "header": [],
            "url": {
              "raw": "{{baseUrl}}/api/rentals/active",
              "host": [
                "{{baseUrl}}"
              ],
              "path": [
                "api",
                "rentals",
                "active"
              ]
            }
          }
        },
        {
          "name": "Get rental by id (rental 1)",
          "request": {
            "method": "GET",
            "header": [],
            "url": {
              "raw": "{{baseUrl}}/api/rentals/1",
              "host": [
                "{{baseUrl}}"
              ],
              "path": [
                "api",
                "rentals",
                "1"
              ]
            }
          }
        },
        {
          "name": "Return rental 1 (Ana returns Jurassic Park)",
          "request": {
            "method": "POST",
            "header": [],
            "url": {
              "raw": "{{baseUrl}}/api/rentals/return/1",
              "host": [
                "{{baseUrl}}"
              ],
              "path": [
                "api",
                "rentals",
                "return",
                "1"
              ]
            }
          }
        },
        {
          "name": "Return rental 1 again (should fail)",
          "request": {
            "method": "POST",
            "header": [],
            "url": {
              "raw": "{{baseUrl}}/api/rentals/return/1",
              "host": [
                "{{baseUrl}}"
              ],
              "path": [
                "api",
                "rentals",
                "return",
                "1"
              ]
            }
          }
        },
        {
          "name": "Get rentals for user Ana (user 1)",
          "request": {
            "method": "GET",
            "header": [],
            "url": {
              "raw": "{{baseUrl}}/api/rentals/user/1",
              "host": [
                "{{baseUrl}}"
              ],
              "path": [
                "api",
                "rentals",
                "user",
                "1"
              ]
            }
          }
        }
      ]
    },
    {
      "name": "Reviews (Special Feature)",
      "item": [
        {
          "name": "Get reviews for VHS 1 (initially empty)",
          "request": {
            "method": "GET",
            "header": [],
            "url": {
              "raw": "{{baseUrl}}/api/reviews/vhs/1",
              "host": [
                "{{baseUrl}}"
              ],
              "path": [
                "api",
                "reviews",
                "vhs",
                "1"
              ]
            }
          }
        },
        {
          "name": "Create review - Ana rates Jurassic Park 5",
          "request": {
            "method": "POST",
            "header": [
              {
                "key": "Content-Type",
                "value": "application/json"
              }
            ],
            "body": {
              "mode": "raw",
              "raw": "{\n  \"userId\": 1,\n  \"vhsId\": 1,\n  \"rating\": 5,\n  \"comment\": \"Classic masterpiece!\"\n}"
            },
            "url": {
              "raw": "{{baseUrl}}/api/reviews",
              "host": [
                "{{baseUrl}}"
              ],
              "path": [
                "api",
                "reviews"
              ]
            }
          }
        },
        {
          "name": "Create review - Marko rates Jurassic Park 4",
          "request": {
            "method": "POST",
            "header": [
              {
                "key": "Content-Type",
                "value": "application/json"
              }
            ],
            "body": {
              "mode": "raw",
              "raw": "{\n  \"userId\": 2,\n  \"vhsId\": 1,\n  \"rating\": 4,\n  \"comment\": \"Still great!\"\n}"
            },
            "url": {
              "raw": "{{baseUrl}}/api/reviews",
              "host": [
                "{{baseUrl}}"
              ],
              "path": [
                "api",
                "reviews"
              ]
            }
          }
        },
        {
          "name": "Create review - duplicate review by Ana for Jurassic Park (should fail)",
          "request": {
            "method": "POST",
            "header": [
              {
                "key": "Content-Type",
                "value": "application/json"
              }
            ],
            "body": {
              "mode": "raw",
              "raw": "{\n  \"userId\": 1,\n  \"vhsId\": 1,\n  \"rating\": 3,\n  \"comment\": \"Second review should not be allowed.\"\n}"
            },
            "url": {
              "raw": "{{baseUrl}}/api/reviews",
              "host": [
                "{{baseUrl}}"
              ],
              "path": [
                "api",
                "reviews"
              ]
            }
          }
        },
        {
          "name": "Create review - invalid rating (should fail validation)",
          "request": {
            "method": "POST",
            "header": [
              {
                "key": "Content-Type",
                "value": "application/json"
              }
            ],
            "body": {
              "mode": "raw",
              "raw": "{\n  \"userId\": 3,\n  \"vhsId\": 2,\n  \"rating\": 6,\n  \"comment\": \"Too high rating.\"\n}"
            },
            "url": {
              "raw": "{{baseUrl}}/api/reviews",
              "host": [
                "{{baseUrl}}"
              ],
              "path": [
                "api",
                "reviews"
              ]
            }
          }
        },
        {
          "name": "Get reviews for VHS 1 (after adding reviews)",
          "request": {
            "method": "GET",
            "header": [],
            "url": {
              "raw": "{{baseUrl}}/api/reviews/vhs/1",
              "host": [
                "{{baseUrl}}"
              ],
              "path": [
                "api",
                "reviews",
                "vhs",
                "1"
              ]
            }
          }
        },
        {
          "name": "Get VHS 1 details with average rating",
          "request": {
            "method": "GET",
            "header": [],
            "url": {
              "raw": "{{baseUrl}}/api/vhs/1/details",
              "host": [
                "{{baseUrl}}"
              ],
              "path": [
                "api",
                "vhs",
                "1",
                "details"
              ]
            }
          }
        }
      ]
    }
  ]
}